KEGGutils/KEGGapi.py
KEGGutils/KEGGerrors.py
KEGGutils/KEGGgraphs.py
KEGGutils/KEGGhelpers.py
KEGGutils/KEGGpathway.py
KEGGutils/KEGGutils.py
KEGGutils/__init__.py
KEGGutils-0.4.0.dist-info/METADATA
KEGGutils-0.4.0.dist-info/WHEEL
KEGGutils-0.4.0.dist-info/top_level.txt
KEGGutils-0.4.0.dist-info/RECORD
