Metadata-Version: 2.1
Name: KEGGutils
Version: 0.4.0
Summary: Simple utils to work with KEGG data on NetworkX
Home-page: https://github.com/filippocastelli/KEGGutils
Author: Filippo Castelli
Author-email: filippocastelli42@gmail.com
License: Unlicense
Keywords: KEGG networkx utils
Classifier: Development Status :: 3 - Alpha
Classifier: Topic :: Utilities
Classifier: License :: Public Domain
Requires-Dist: networkx
Requires-Dist: matplotlib
Requires-Dist: awesome-slugify
Requires-Dist: requests
Requires-Dist: Pillow
Requires-Dist: scipy
Requires-Dist: pytest
Requires-Dist: pytest-cov
Requires-Dist: jupyter
